Metadata-Version: 2.1
Name: pytescomobileirl
Version: 0.2.4
Summary: Unofficial Python Tesco Mobile (Ireland) API
Home-page: https://github.com/skhg/pytescomobileirl
Author: Jack Higgins
Author-email: pypi@jackhiggins.ie
License: MIT
Keywords: tesco mobile phone balance status web ireland api
Platform: UNKNOWN
Classifier: Development Status :: 4 - Beta
Classifier: License :: OSI Approved :: MIT License
Classifier: Programming Language :: Python :: 2.7
Classifier: Programming Language :: Python :: 3.6
